pietoolz/__init__.py
pietoolz/cool_stuff/__init__.py
pietoolz/cool_stuff/poker.py
pietoolz/cool_stuff/poker_exceptions.py
pietoolz/cool_stuff/quotationz_n_rotationz.py
pietoolz/data_structures/__init__.py
pietoolz/data_structures/bst.py
pietoolz/data_structures/coord.py
pietoolz/data_structures/queue.py
pietoolz/data_structures/stack.py
pietoolz/dev_tools/__init__.py
pietoolz/dev_tools/time.py
pietoolz/dev_toolz/__init__.py
pietoolz/dev_toolz/utils.py
pietoolz/dev_toolz/cool_stuff/__init__.py
pietoolz/dev_toolz/cool_stuff/poker.py
pietoolz/dev_toolz/cool_stuff/poker_exceptions.py
pietoolz/dev_toolz/math_stuff/__init__.py
pietoolz/dev_toolz/math_stuff/math.py
pietoolz/dev_toolz/time_stuff/__init__.py
pietoolz/dev_toolz/time_stuff/time.py
pietoolz/proj7_matter/__init__.py
pietoolz/proj7_matter/atom.py
proj7_matter/__init__.py
proj7_matter/atom.py
pietoolz-0.0.10.dist-info/LICENSE
pietoolz-0.0.10.dist-info/METADATA
pietoolz-0.0.10.dist-info/WHEEL
pietoolz-0.0.10.dist-info/top_level.txt
pietoolz-0.0.10.dist-info/RECORD
