Metadata-Version: 2.1
Name: pietoolz
Version: 0.0.10
Summary: PieToolz makes life easier.
Author: coolhuip
Author-email: cool.huip@example.com
License-File: LICENSE
